{
  "words": [
    {
      "id": "632c413c-7dec-4a9d-9ab8-b8ad4e78e212",
      "dutch": "precieze",
      "farsi": "دقیق"
    },
    {
      "id": "daa6b783-22d2-4c38-b4bb-6dfd5fe08034",
      "dutch": "vertaling",
      "farsi": "ترجمه"
    },
    {
      "id": "cc45a497-b330-42cd-9053-82ec04128502",
      "dutch": "tekst",
      "farsi": "متن"
    },
    {
      "id": "99e8a88a-9210-407c-8cfa-c3dab50359ee",
      "dutch": "waarom",
      "farsi": "چرا"
    },
    {
      "id": "b77b6912-07c8-4541-bf7b-2c20f8132b2a",
      "dutch": "sommige",
      "farsi": "برخی"
    },
    {
      "id": "e2f4e16c-a8dc-4370-90ab-d25fd656aeea",
      "dutch": "mensen",
      "farsi": "مردم/افراد"
    },
    {
      "id": "d65fc1e1-a94e-4429-bcd2-436a50e46fe6",
      "dutch": "slapen",
      "farsi": "خوابیدن"
    },
    {
      "id": "6e5fc130-7ae0-40b8-a59b-13c525418f17",
      "dutch": "belangrijke",
      "farsi": "مهم"
    },
    {
      "id": "952a1553-9518-43b1-a695-cd85bbdca6cc",
      "dutch": "woorden",
      "farsi": "کلمات"
    },
    {
      "id": "15e835fe-29fe-4ce0-93a1-fdf2dc73e5e1",
      "dutch": "vraag",
      "farsi": "سوال"
    },
    {
      "id": "66f27ce8-0dd3-40c2-9272-8a256bb53487",
      "dutch": "onderzoekt",
      "farsi": "بررسی می‌کند"
    },
    {
      "id": "83ef0c91-306c-479e-98f5-a9e403d2b2c6",
      "dutch": "bepaalde",
      "farsi": "معین/خاص"
    },
    {
      "id": "41d6e7d5-8231-4067-babb-50d02493c0bf",
      "dutch": "patroon",
      "farsi": "الگو"
    },
    {
      "id": "6452037f-88a0-4295-83f4-91a071277a98",
      "dutch": "ontwikkeld",
      "farsi": "توسعه یافته"
    },
    {
      "id": "41d1c9e6-4f28-447f-9910-3d42f067d4c8",
      "dutch": "nacht",
      "farsi": "شب"
    },
    {
      "id": "f66e7b38-88d5-48a5-a307-ef1e1ed3fd7f",
      "dutch": "bed",
      "farsi": "تخت"
    },
    {
      "id": "81d26d65-9764-47b1-ac71-78e19a32576e",
      "dutch": "conventioneel",
      "farsi": "متعارف/معمول"
    }
  ],
  "currentTest": {
    "id": "gh8qa2uct",
    "type": "dutch_to_farsi",
    "question": "معنی کلمه «bed» چیست؟",
    "correctAnswer": "تخت",
    "options": [
      "ترجمه",
      "خوابیدن",
      "تخت"
    ],
    "explanation": "کلمه «bed» به معنی «تخت» است."
  },
  "testScore": 20,
  "testTotal": 28
}